AK_Repo_pypi/__init__.py
AK_Repo_pypi/perceptron.py
AK_Repo_pypi_midofemi-0.0.3.dist-info/LICENSE
AK_Repo_pypi_midofemi-0.0.3.dist-info/METADATA
AK_Repo_pypi_midofemi-0.0.3.dist-info/WHEEL
AK_Repo_pypi_midofemi-0.0.3.dist-info/top_level.txt
AK_Repo_pypi_midofemi-0.0.3.dist-info/RECORD
