Metadata-Version: 2.1
Name: AK-Repo-pypi-midofemi
Version: 0.0.3
Summary: its an implimentation of Perceptron
Home-page: https://github.com/midofemi/AK_Repo_pypi
Author: midofemi
Author-email: midofemi@yahoo.com
Project-URL: Bug Tracker, https://github.com/midofemi/AK_Repo_pypi/issues
Classifier: Programming Language :: Python :: 3
Classifier: License :: OSI Approved :: MIT License
Classifier: Operating System :: OS Independent
Requires-Python: >=3.7
License-File: LICENSE
Requires-Dist: numpy
Requires-Dist: tqdm
